LICENSE
MANIFEST.in
setup.py
myshows/__init__.py
myshows/api.py
myshows/apiv2.py
myshows/exceptions.py
myshows/test.py
myshows/test_config.py
myshows/testapi2.py
myshows/urls.py
myshows.egg-info/PKG-INFO
myshows.egg-info/SOURCES.txt
myshows.egg-info/dependency_links.txt
myshows.egg-info/requires.txt
myshows.egg-info/top_level.txt