Metadata-Version: 1.1
Name: myshows
Version: 0.0.3.5
Summary: This is a myshows.me Python API
Home-page: https://github.com/farestz/myshows-python3
Author: Alexander Basov
Author-email: farestz@gmail.com
License: MIT License
Keywords: myshows.me api myshows shows
Platform: UNKNOWN
Classifier: Environment :: Web Environment
Classifier: Intended Audience :: Developers
Classifier: License :: OSI Approved :: MIT License
Classifier: Programming Language :: Python :: 3.3
Classifier: Programming Language :: Python :: 3.4
Classifier: Programming Language :: Python :: 3.5
Classifier: Topic :: Software Development :: Libraries :: Python Modules
